odoo/addons/l10n_fr_hr_check_ssnid/README.rst
odoo/addons/l10n_fr_hr_check_ssnid/__init__.py
odoo/addons/l10n_fr_hr_check_ssnid/__manifest__.py
odoo/addons/l10n_fr_hr_check_ssnid/i18n/es.po
odoo/addons/l10n_fr_hr_check_ssnid/i18n/fr.po
odoo/addons/l10n_fr_hr_check_ssnid/i18n/l10n_fr_hr_check_ssnid.pot
odoo/addons/l10n_fr_hr_check_ssnid/models/__init__.py
odoo/addons/l10n_fr_hr_check_ssnid/models/hr_employee.py
odoo/addons/l10n_fr_hr_check_ssnid/readme/CONTRIBUTORS.md
odoo/addons/l10n_fr_hr_check_ssnid/readme/DESCRIPTION.md
odoo/addons/l10n_fr_hr_check_ssnid/readme/INSTALL.md
odoo/addons/l10n_fr_hr_check_ssnid/readme/USAGE.md
odoo/addons/l10n_fr_hr_check_ssnid/static/description/icon.png
odoo/addons/l10n_fr_hr_check_ssnid/static/description/index.html
odoo/addons/l10n_fr_hr_check_ssnid/tests/__init__.py
odoo/addons/l10n_fr_hr_check_ssnid/tests/test_ssnid.py
odoo_addon_l10n_fr_hr_check_ssnid-18.0.1.0.0.4.dist-info/METADATA
odoo_addon_l10n_fr_hr_check_ssnid-18.0.1.0.0.4.dist-info/WHEEL
odoo_addon_l10n_fr_hr_check_ssnid-18.0.1.0.0.4.dist-info/top_level.txt
odoo_addon_l10n_fr_hr_check_ssnid-18.0.1.0.0.4.dist-info/RECORD
